IpfsCaozuoXuexiJiaocheng/README.md
IpfsCaozuoXuexiJiaocheng/__init__.py
IpfsCaozuoXuexiJiaocheng/__main__.py
IpfsCaozuoXuexiJiaocheng/file.epub
IpfsCaozuoXuexiJiaocheng/index.html
IpfsCaozuoXuexiJiaocheng/css/__init__.py
IpfsCaozuoXuexiJiaocheng/css/annotations.css
IpfsCaozuoXuexiJiaocheng/css/main.css
IpfsCaozuoXuexiJiaocheng/css/normalize.css
IpfsCaozuoXuexiJiaocheng/css/popup.css
IpfsCaozuoXuexiJiaocheng/font/__init__.py
IpfsCaozuoXuexiJiaocheng/font/fontello.eot
IpfsCaozuoXuexiJiaocheng/font/fontello.svg
IpfsCaozuoXuexiJiaocheng/font/fontello.ttf
IpfsCaozuoXuexiJiaocheng/font/fontello.woff
IpfsCaozuoXuexiJiaocheng/img/__init__.py
IpfsCaozuoXuexiJiaocheng/img/annotator-glyph-sprite.png
IpfsCaozuoXuexiJiaocheng/img/annotator-icon-sprite.png
IpfsCaozuoXuexiJiaocheng/img/apple-touch-icon.png
IpfsCaozuoXuexiJiaocheng/img/cancelfullscreen.png
IpfsCaozuoXuexiJiaocheng/img/close.png
IpfsCaozuoXuexiJiaocheng/img/fullscreen.png
IpfsCaozuoXuexiJiaocheng/img/loader.gif
IpfsCaozuoXuexiJiaocheng/img/menu-icon.png
IpfsCaozuoXuexiJiaocheng/img/save.png
IpfsCaozuoXuexiJiaocheng/img/saved.png
IpfsCaozuoXuexiJiaocheng/img/settings-s.png
IpfsCaozuoXuexiJiaocheng/img/settings.png
IpfsCaozuoXuexiJiaocheng/img/star.png
IpfsCaozuoXuexiJiaocheng/js/__init__.py
IpfsCaozuoXuexiJiaocheng/js/epub.js
IpfsCaozuoXuexiJiaocheng/js/epub.min.js
IpfsCaozuoXuexiJiaocheng/js/epub.min.map
IpfsCaozuoXuexiJiaocheng/js/hooks.min.js
IpfsCaozuoXuexiJiaocheng/js/hooks.min.map
IpfsCaozuoXuexiJiaocheng/js/reader.js
IpfsCaozuoXuexiJiaocheng/js/reader.js.map
IpfsCaozuoXuexiJiaocheng/js/reader.min.js
IpfsCaozuoXuexiJiaocheng/js/reader.min.map
IpfsCaozuoXuexiJiaocheng/js/hooks/__init__.py
IpfsCaozuoXuexiJiaocheng/js/hooks/extensions/__init__.py
IpfsCaozuoXuexiJiaocheng/js/hooks/extensions/highlight.js
IpfsCaozuoXuexiJiaocheng/js/libs/__init__.py
IpfsCaozuoXuexiJiaocheng/js/libs/jquery.min.js
IpfsCaozuoXuexiJiaocheng/js/libs/localforage.min.js
IpfsCaozuoXuexiJiaocheng/js/libs/screenfull.js
ipfs_caozuo_xuexi_jiaocheng-2024.3.4.0.dist-info/METADATA
ipfs_caozuo_xuexi_jiaocheng-2024.3.4.0.dist-info/WHEEL
ipfs_caozuo_xuexi_jiaocheng-2024.3.4.0.dist-info/entry_points.txt
ipfs_caozuo_xuexi_jiaocheng-2024.3.4.0.dist-info/top_level.txt
ipfs_caozuo_xuexi_jiaocheng-2024.3.4.0.dist-info/RECORD
